equine/NOTICE.txt
equine/__init__.py
equine/_version.py
equine/equine.py
equine/equine_gp.py
equine/equine_output.py
equine/equine_protonet.py
equine/load_equine_model.py
equine/py.typed
equine/utils.py
equine-0.1.6.dist-info/licenses/LICENSE.md
equine-0.1.6.dist-info/METADATA
equine-0.1.6.dist-info/WHEEL
equine-0.1.6.dist-info/top_level.txt
equine-0.1.6.dist-info/RECORD
