Metadata-Version: 2.4
Name: equine
Version: 0.1.6
Summary: EQUINE^2: Establishing Quantified Uncertainty for Neural Networks
Author: Allan Wollaber, Steven Jorgensen, John Holodnak, Jensen Dempsey, Harry Li
Maintainer: Allan Wollaber, Steven Jorgensen
License: MIT
Project-URL: Homepage, https://mit-ll-responsible-ai.github.io/equine/
Project-URL: Bug Tracker, https://github.com/mit-ll-responsible-ai/equine/issues
Project-URL: Source, https://github.com/mit-ll-responsible-ai/equine
Keywords: machine learning,robustness,pytorch,responsible,AI
Classifier: Development Status :: 4 - Beta
Classifier: License :: OSI Approved :: MIT License
Classifier: Operating System :: OS Independent
Classifier: Intended Audience :: Science/Research
Classifier: Topic :: Scientific/Engineering
Classifier: Programming Language :: Python :: 3 :: Only
Requires-Python: >=3.9
License-File: LICENSE.md
Requires-Dist: torch<2.3.0,>=1.10.0; platform_machine == "x86_64" and sys_platform == "darwin"
Requires-Dist: torch<2.10.0,>=2.0.0; platform_machine != "x86_64" or sys_platform != "darwin"
Requires-Dist: torchmetrics>=0.6.0
Requires-Dist: numpy<2.0.0,>=1.22.0; platform_machine == "x86_64" and sys_platform == "darwin"
Requires-Dist: numpy<=2.4.0,>=1.22.0; platform_machine != "x86_64" or sys_platform != "darwin"
Requires-Dist: tqdm
Requires-Dist: beartype
Requires-Dist: icontract
Requires-Dist: scipy<1.17.0; platform_machine == "x86_64" and sys_platform == "darwin"
Requires-Dist: scipy; platform_machine != "x86_64" or sys_platform != "darwin"
Provides-Extra: tests
Requires-Dist: pytest>=3.8; extra == "tests"
Requires-Dist: pytest-cov; extra == "tests"
Requires-Dist: hypothesis<6.151.0,>=6.105.0; extra == "tests"
Requires-Dist: pre-commit>=2.19; extra == "tests"
Requires-Dist: codespell; extra == "tests"
Provides-Extra: docs
Requires-Dist: mkdocs>=1.3; extra == "docs"
Requires-Dist: mkdocs-material; extra == "docs"
Requires-Dist: mkdocstrings-python; extra == "docs"
Requires-Dist: mkdocs-jupyter; extra == "docs"
Requires-Dist: mkdocs-literate-nav; extra == "docs"
Requires-Dist: mkdocs-gen-files; extra == "docs"
Requires-Dist: mkdocs-section-index; extra == "docs"
Dynamic: license-file
